{
  "filename": "PanelElementLayout2.mcr",
  "status": "completed",
  "total_tokens": 58966,
  "processing_time": 1316.368215560913,
  "passes": {
    "1": {
      "success": true,
      "data": {
        "raw_content": "```json\n{\n  \"header\": {\n    \"type\": null,\n    \"numBeamsReq\": null,\n    \"keywords\": null,\n   "
      },
      "tokens_used": 8937,
      "error": null
    },
    "2": {
      "success": true,
      "data": {
        "usageEnvironment": {
          "primarySpace": "PaperSpace",
          "supportsPaperSpace": true,
          "isShopDrawingScript": true,
          "isMultipageScript": false,
          "detectionEvidence": "Header comments explicitly state 'For use on a static HSB Viewport in PS' and 'Primarily intended to be inserted by the user on PS Viewports'. The script uses `getViewport(T(\"Select a viewport\"))` to retrieve a `Viewport`, stores it in `_Viewport`, and calculates coordinate transformations (`CoordSys ms2ps = vp.coordSys()`, `CoordSys ps2ms`). It generates dimensions using `Display` objects (`dp`, `dpFar`) which are then transformed to Paper Space using `dmNear.transformBy(ms2ps)`. It retrieves the element from the viewport (`Element el = vp.element()`) rather than selecting it directly from Model Space."
        },
        "prerequisites": {
          "requiredEntities": [
            "Viewport",
            "Element (ElementWall with Sips)"
          ],
          "minimumBeams": 0,
          "requiredSpace": "Must be inserted in Paper Space on a layout containing a viewport linked to a valid Element (Wall) that contains Sips.",
          "requiredSettings": []
        }
      },
      "tokens_used": 5455,
      "error": null
    },
    "3": {
      "success": true,
      "data": {
        "raw_content": "```json\n{\n  \"commandLine\": {\n    \"insertionFlow\": [\n      {\n        \"step\": 1,\n        \"function\": \"getViewport\",\n        \"promptOriginal\": \"Select a viewport\",\n        \"condition\": \"_bOnInsert\",\n        \"required\": true\n      }\n    ],\n    \"keywordOptions\": []\n  },\n  \"dialogs\": [],\n  \"opmProperties\": [\n    {\n      \"index\": 0,\n      \"variable\": \"psDimStyle\",\n      \"type\": \"PropString\",\n      \"displayName\": \"Dimension Style Near\",\n      \"defaultValue\": null,\n      \"inputType\": \"dropdown\",\n      \"options\": [],\n      \"category\": null,\n      \"description\": null\n    },\n    {\n      \"index\": 2,\n      \"variable\": \"psDimStyleFar\",\n      \"type\": \"PropString\",\n      \"displayName\": \"Dimension Style Far\",\n      \"defaultValue\": null,\n      \"inputType\": \"dropdown\",\n      \"options\": [],\n      \"category\": null,\n      \"description\": null\n    },\n    {\n      \"index\": 17,\n      \"variable\": \"psBeamDimstyle\",\n      \"type\": \"PropString\",\n      \"displayName\": \"Beam Dimstyle\",\n      \"defaultValue\": 1,\n      \"inputType\": \"dropdown\",\n      \"options\": [\n        \"Do Not Dimension\",\n        \"Combine with Near\"\n      ],\n      \"category\": null,\n      \"description\": null\n    },\n    {\n      \"index\": 0,\n      \"variable\": \"pdChainSpace\",\n      \"type\": \"PropDouble\",\n      \"displayName\": \"Dimension Chain Spacing\",\n      \"defaultValue\": \"1\",\n      \"inputType\": \"number\",\n      \"options\": [],\n      \"category\": null,\n      \"description\": null\n    },\n    {\n      \"index\": 1,\n      \"variable\": \"pdDimPointTol\",\n      \"type\": \"PropDouble\",\n      \"displayName\": \"Dimension point tolerance\",\n      \"defaultValue\": \".125\",\n      \"inputType\": \"number\",\n      \"options\": [],\n      \"category\": null,\n      \"description\": null\n    },\n    {\n      \"index\": 1,\n      \"variable\": \"psDimLimit\",\n      \"type\": \"PropString\",\n      \"displayName\": \"Limit Extension Lines\",\n      \"defaultValue\": \"Yes\",\n      \"inputType\": \"dropdown\",\n      \"options\": [\n        \"Yes\",\n        \"No\"\n      ],\n      \"category\": null,\n      \"description\": null\n    },\n    {\n      \"index\": 3,\n      \"variable\": \"psDimWhat\",\n      \"type\": \"PropString\",\n      \"displayName\": \"Detail Level\",\n      \"defaultValue\": null,\n      \"inputType\": \"dropdown\",\n      \"options\": [\n        \"Extremes\",\n        \"All Points\"\n      ],\n      \"category\": null,\n      \"description\": null\n    },\n    {\n      \"index\": 4,\n      \"variable\": \"psDrawTopDim\",\n      \"type\": \"PropString\",\n      \"displayName\": \"Display Top Dim\",\n      \"defaultValue\": null,\n      \"inputType\": \"dropdown\",\n      \"options\": [\n        \"Yes\",\n        \"No\"\n      ],\n      \"category\": null,\n      \"description\": null\n    },\n    {\n      \"index\": 5,\n      \"variable\": \"psDrawBotDim\",\n      \"type\": \"PropString\",\n      \"displayName\": \"Display Bottom Dim\",\n      \"defaultValue\": null,\n      \"inputType\": \"dropdown\",\n      \"options\": [\n        \"Yes\",\n        \"No\"\n      ],\n      \"category\": null,\n      \"description\": null\n    },\n    {\n      \"index\": 6,\n      \"variable\": \"psDrawLeftDim\",\n      \"type\": \"PropString\",\n      \"displayName\": \"Display Left Dim\",\n      \"defaultValue\": null,\n      \"inputType\": \"dropdown\",\n      \"options\": [\n        \"Yes\",\n        \"No\"\n      ],\n      \"category\": null,\n      \"description\": null\n    },\n    {\n      \"index\": 7,\n      \"variable\": \"psDrawRightDim\",\n      \"type\": \"PropString\",\n      \"displayName\": \"Display Right Dim\",\n      \"defaultValue\": null,\n      \"inputType\": \"dropdown\",\n      \"options\": [\n        \"Yes\",\n        \"No\"\n      ],\n      \"category\": null,\n      \"description\": null\n    },\n    {\n      \"index\": 8,\n      \"variable\": \"psDimConnectedElements\",\n      \"type\": \"PropString\",\n      \"displayName\": \"Dim Connected Female Elements\",\n      \"defaultValue\": null,\n      \"inputType\": \"dropdown\",\n      \"options\": [\n        \"Yes\",\n        \"No\"\n      ],\n      \"category\": null,\n      \"description\": null\n    },\n    {\n      \"index\": 9,\n      \"variable\": \"psUseGrips\",\n      \"type\": \"PropString\",\n      \"displayName\": \"Use Grips\",\n      \"defaultValue\": null,\n      \"inputType\": \"dropdown\",\n      \"options\": [\n        \"Yes\",\n        \"No\"\n      ],\n      \"category\": null,\n      \"description\": null\n    },\n    {\n      \"index\": 2,\n      \"variable\": \"pdDimOffTop\",\n      \"type\": \"PropDouble\",\n      \"displayName\": \"Top Dim Offset\",\n      \"defaultValue\": \"12\",\n      \"inputType\": \"number\",\n      \"options\": [],\n      \"category\": null,\n      \"description\": null\n    },\n    {\n      \"index\": 3,\n      \"variable\": \"pdDimOffBot\",\n      \"type\": \"PropDouble\",\n      \"displayName\": \"Bottom Dim Offset\",\n      \"defaultValue\": \"12\",\n      \"inputType\": \"number\",\n      \"options\": [],\n      \"category\": null,\n      \"description\": null\n    },\n    {\n      \"index\": 4,\n      \"variable\": \"pdDimOffLeft\",\n      \"type\": \"PropDouble\",\n      \"displayName\": \"Left Dim Offset\",\n      \"defaultValue\": \"12\",\n      \"inputType\": \"number\",\n      \"options\": [],\n      \"category\": null,\n      \"description\": null\n    },\n    {\n      \"index\": 5,\n      \"variable\": \"pdDimOffRight\",\n      \"type\": \"PropDouble\",\n      \"displayName\": \"Right Dim Offset\",\n      \"defaultValue\": \"12\",\n      \"inputType\": \"number\",\n      \"options\": [],\n      \"category\": null,\n      \"description\": null\n    },\n    {\n      \"index\": 10,\n      \"variable\": \"psAddSipPtsLeft\",\n      \"type\": \"PropString\",\n      \"displayName\": \"Add Sip Points Left\",\n      \"defaultValue\": null,\n      \"inputType\": \"dropdown\",\n      \"options\": [\n        \"Yes\",\n        \"No\"\n      ],\n      \"category\": null,\n      \"description\": null\n    },\n    {\n      \"index\": 11,\n      \"variable\": \"psAddSipPtsRight\",\n      \"type\": \"PropString\",\n      \"displayName\": \"Add Sip Points Right\",\n      \"defaultValue\": null,\n      \"inputType\": \"dropdown\",\n      \"options\": [\n        \"Yes\",\n        \"No\"\n      ],\n      \"category\": null,\n      \"description\": null\n    },\n    {\n      \"index\": 12,\n      \"variable\": \"psDimTypeTop\",\n      \"type\": \"PropString\",\n      \"displayName\": \"Top Dim Type\",\n      \"defaultValue\": null,\n      \"inputType\": \"dropdown\",\n      \"options\": [\n        \"Delta\",\n        \"Cummulative\",\n        \"Both\"\n      ],\n      \"category\": null,\n      \"description\": null\n    },\n    {\n      \"index\": 13,\n      \"variable\": \"psDimTypeBot\",\n      \"type\": \"PropString\",\n      \"displayName\": \"Bottom"
      },
      "tokens_used": 9774,
      "error": null
    },
    "4": {
      "success": true,
      "data": {
        "raw_content": "```json\n{\n  \"scriptPurpose\": {\n    \"summary\": \"Automatically generates dimension lines for Wall or Roof elements in Paper Space viewports, including overall dimensions, individual panel details (SIPs), and openings.\",\n    \"category\": \"ShopDrawing\",\n    \"typicalUseCase\": \"Used during the detailing phase to create clean, automatic elevation dimensions for panelized wall layouts on production drawings.\"\n  },\n  \"parameters\": [\n    {\n      \"name\": \"psDimStyle\",\n      \"technicalDefault\": \"First item in _DimStyles\",\n      \"businessMeaning\": \"Selects the visual style (text size, arrow style, precision) for dimensions on the front (Near) face of the element.\",\n      \"validRange\": \"Any dimension style defined in the drawing template.\",\n      \"unit\": \"N/A (Style Name)\",\n      \"affectsOutput\": \"Changes the text height, arrowheads, and precision of the primary dimensions.\"\n    },\n    {\n      \"name\": \"psDimStyleFar\",\n      \"technicalDefault\": \"First item in _DimStyles\",\n      \"businessMeaning\": \"Selects the visual style for dimensions on the back (Far) face of the element.\",\n      \"validRange\": \"Any dimension style defined in the drawing template.\",\n      \"unit\": \"N/A (Style Name)\",\n      \"affectsOutput\": \"Changes the appearance of secondary dimensions, allowing distinction between near and far side geometry.\"\n    },\n    {\n      \"name\": \"psBeamDimstyle\",\n      \"technicalDefault\": \"1 (Combine with Near)\",\n      \"businessMeaning\": \"Determines how to handle beams inside the wall/roof.\",\n      \"validRange\": \"0 (Do Not Dimension), 1 (Combine with Near)\",\n      \"unit\": \"Index\",\n      \"affectsOutput\": \"If 'Combine with Near', internal beam locations are added to the primary dimension chain. If 'Do Not Dimension', beams are ignored.\"\n    },\n    {\n      \"name\": \"pdChainSpace\",\n      \"technicalDefault\": \"1 (unit length)\",\n      \"businessMeaning\": \"The vertical or horizontal distance between stacked dimension lines (e.g., between the overall dimension and the detailed opening dimensions).\",\n      \"validRange\": \"5mm - 20mm (approx 0.2\\\" - 0.75\\\")\",\n      \"unit\": \"Length (mm/inch)\",\n      \"affectsOutput\": \"Increases or decreases the gap between parallel dimension lines to prevent text overlap.\"\n    },\n    {\n      \"name\": \"pdDimPointTol\",\n      \"technicalDefault\": \"0.125 (unit length)\",\n      \"businessMeaning\": \"The distance threshold used to merge two dimension points into one. Prevents cluttered dimensions caused by minor geometry irregularities.\",\n      \"validRange\": \"1mm - 10mm (approx 0.04\\\" - 0.4\\\")\",\n      \"unit\": \"Length (mm/inch)\",\n      \"affectsOutput\": \"If set too low, duplicate dimensions appear for nearly coincident points. If set too high, distinct features are merged.\"\n    },\n    {\n      \"name\": \"psDimLimit\",\n      \"technicalDefault\": \"Yes\",\n      \"businessMeaning\": \"Controls whether dimension extension lines stop at the dimension line (Yes) or extend all the way to the geometry (No).\",\n      \"validRange\": \"Yes, No\",\n      \"unit\": \"Boolean\",\n      \"affectsOutput\": \"'Yes' creates cleaner drawings with short ticks. 'No' shows exactly where the dimension point relates to the model geometry.\"\n    },\n    {\n      \"name\": \"psDimWhat\",\n      \"technicalDefault\": \"Extremes\",\n      \"businessMeaning\": \"Specifies the level of detail for the dimensions.\",\n      \"validRange\": \"Extremes, All Points\",\n      \"unit\": \"Option\",\n      \"affectsOutput\": \"'Extremes' only dimensions the total width/height. 'All Points' dimensions every opening, corner, and joint along the wall.\"\n    },\n    {\n      \"name\": \"psDrawTopDim\",\n      \"technicalDefault\": \"Yes\",\n      \"businessMeaning\": \"Visibility toggle for the dimension line on the top side of the element.\",\n      \"validRange\": \"Yes, No\",\n      \"unit\": \"Boolean\",\n      \"affectsOutput\": \"Suppresses or shows the horizontal dimension at the top of the elevation.\"\n    },\n    {\n      \"name\": \"psDrawBotDim\",\n      \"technicalDefault\": \"Yes\",\n      \"businessMeaning\": \"Visibility toggle for the dimension line on the bottom side of the element.\",\n      \"validRange\": \"Yes, No\",\n      \"unit\": \"Boolean\",\n      \"affectsOutput\": \"Suppresses or shows the horizontal dimension at the bottom (sill line) of the elevation.\"\n    },\n    {\n      \"name\": \"psDrawLeftDim\",\n      \"technicalDefault\": \"Yes\",\n      \"businessMeaning\": \"Visibility toggle for the dimension line on the left side of the element.\",\n      \"validRange\": \"Yes, No\",\n      \"unit\": \"Boolean\",\n      \"affectsOutput\": \"Suppresses or shows the vertical dimension on the left.\"\n    },\n    {\n      \"name\": \"psDrawRightDim\",\n      \"technicalDefault\": \"Yes\",\n      \"businessMeaning\": \"Visibility toggle for the dimension line on the right side of the element.\",\n      \"validRange\": \"Yes, No\",\n      \"unit\": \"Boolean\",\n      \"affectsOutput\": \"Suppresses or shows the vertical dimension on the right.\"\n    },\n    {\n      \"name\": \"psDimConnectedElements\",\n      \"technicalDefault\": \"Yes\",\n      \"businessMeaning\": \"Controls whether to include dimensions for intersecting walls (female elements) attached to the main wall.\",\n      \"validRange\": \"Yes, No\",\n      \"unit\": \"Boolean\",\n      \"affectsOutput\": \"If 'Yes', dimensions for intersecting partition walls or gable returns are included in the chain.\"\n    },\n    {\n      \"name\": \"psUseGrips\",\n      \"technicalDefault\": \"Yes\",\n      \"businessMeaning\": \"Enables interactive handles (grips) on the dimension lines in AutoCAD.\",\n      \"validRange\": \"Yes, No\",\n      \"unit\": \"Boolean\",\n      \"affectsOutput\": \"Allows the user to click and drag the dimension lines to adjust their position after creation.\"\n    },\n    {\n      \"name\": \"pdDimOffTop\",\n      \"technicalDefault\": \"12 (unit length)\",\n      \"businessMeaning\": \"The distance from the top of the element geometry to the first dimension line.\",\n      \"validRange\": \"5mm - 50mm (approx 0.2\\\" - 2\\\")\",\n      \"unit\": \"Length (mm/inch)\",\n      \"affectsOutput\": \"Moves the top dimension chain closer or further from the wall.\"\n    },\n    {\n      \"name\": \"pdDimOffBot\",\n      \"technicalDefault\": \"12 (unit length)\",\n      \"businessMeaning\": \"The distance from the bottom of the element geometry to the first dimension line.\",\n      \"validRange\": \"5mm - 50mm (approx 0.2\\\" - 2\\\")\",\n      \"unit\": \"Length (mm/inch)\",\n      \"affectsOutput\": \"Moves the bottom dimension chain closer or further from the wall.\"\n    },\n    {\n      \"name\": \"pdDimOffLeft\",\n      \"technicalDefault\": \"12 (unit length)\",\n      \"businessMeaning\": \"The distance from the left edge of the element geometry to the first dimension line.\",\n      \"validRange\": \"5mm - 50mm (approx 0.2\\\" - 2\\\")\",\n      \"unit\": \"Length (mm/inch)\",\n      \"affectsOutput\": \"Moves the left dimension chain closer or further from the wall.\"\n    },\n    {\n      \"name\": \"pdDimOffRight\",\n      \"technicalDefault\": \"12 (unit length)\",\n      \"businessMeaning\": \"The distance from the right edge of the element geometry to the first dimension line.\",\n      \"validRange\": \"5mm - 50mm (approx 0.2\\\" - 2\\\")\",\n      \"unit\": \"Length (mm/inch)\",\n      \"affectsOutput\": \"Moves the right dimension chain closer or further from the wall.\"\n    },\n    {\n      \"name\": \"psAddSipPtsLeft\",\n      \"technicalDefault\": \"Yes\",\n      \"businessMeaning\": \"Toggles the inclusion of SIP (Structural Insulated Panel) corner points on the left side of the element.\",\n      \"validRange\": \"Yes, No\",\n      \"unit\": \"Boolean\",\n      \"affectsOutput\": \"If 'Yes', the script finds and dimensions the specific panel joints on the left.\"\n    },\n    {\n      \"name\": \"psAddSipPtsRight\",\n      \"technicalDefault\": \"Yes\",\n      \"businessMeaning\": \"Toggles the inclusion of SIP corner points on the right side of the element.\",\n      \"validRange\": \"Yes, No\",\n      \"unit\": \"Boolean\",\n      \"affectsOutput\": \"If 'Yes', the script finds and dimensions the specific panel joints on the right.\"\n    },\n    {\n      \"name\": \"psDimTypeTop\",\n      \"technicalDefault\": \"Delta\",\n      \"businessMeaning\": \"Determines the measurement style for the top dimension chain.\",\n      \"validRange\": \"Delta (individual segments), Cummulative (running total), Both\",\n      \"unit\": \"Option\",\n      \"affectsOutput\": \"Changes whether dimensions show '300, 400, 500' or '300, 700, 1200'.\"\n    },\n    {\n      \"name\": \"psDimTypeBot\",\n      \"technicalDefault\": \"Delta\",\n      \"businessMeaning\": \"Determines the measurement style for the bottom dimension chain.\",\n      \"validRange\": \"Delta (individual segments), Cummulative (running total), Both\",\n      \"unit\": \"Option\",\n      \"affectsOutput\": \"Changes the measurement notation along the bottom.\"\n    },\n    {\n      \"name\": \"psDimTypeLeft\",\n      \"technicalDefault\": \"Delta\",\n      \"businessMeaning\": \"Determines the measurement style for the left dimension chain.\",\n      \"validRange\": \"Delta (individual segments), Cummulative (running total), Both\",\n      \"unit\": \"Option\",\n      \"affectsOutput\": \"Changes the measurement notation along the left.\"\n    },\n    {\n      \"name\": \"psDimTypeRight\",\n      \"technicalDefault\": \"Delta\",\n      \"businessMeaning\": \"Determines the measurement style for the right dimension chain.\",\n      \"validRange\": \"Delta (individual segments), Cummulative (running total), Both\",\n      \"unit\": \"Option\",\n      \"affectsOutput\": \"Changes the measurement notation along the right.\"\n    },\n    {\n      \"name\": \"pdOffLowerPtLeft\",\n      \"technicalDefault\": \"0\",\n      \"businessMeaning\": \"Vertical offset for the zero point of the left dimension chain.\",\n      \"validRange\": \"Any length\",\n      \"unit\": \"Length (mm/inch)\",\n      \"affectsOutput\": \"Shifts the start of the vertical dimension up or down, often used to align with a floor level.\"\n    },\n    {\n      \"name\": \"pdOffLowerPtRight\",\n      \"technicalDefault\": \"0\",\n      \"businessMeaning\": \"Vertical offset for the zero point of the right dimension chain.\",\n      \"validRange\": \"Any length\",\n      \"unit\": \"Length (mm/inch)\",\n      \"affectsOutput\": \"Shifts the start of the vertical dimension up or down.\"\n    },\n    {\n      \"name\": \"pdAddBaseDim\",\n      \"technicalDefault\": \"0\",\n      \"businessMeaning\": \"Adds an additional dimension segment below the bottom of the wall geometry.\",\n      \"validRange\": \"0 (off) or typical wall bottom plate width (e.g., 90mm)\",\n      \"unit\": \"Length (mm/inch)\",\n      \"affectsOutput\": \"Extends the vertical dimension line downwards to indicate a foundation or curb height.\"\n    },\n    {\n      \"name\": \"pdAddElevation\",\n      \"technicalDefault\": \"0\",\n      \"businessMeaning\": \"Adds a constant value to all vertical dimensions (e.g., to convert relative height to Absolute Elevation/RL).\",\n      \"validRange\": \"Site specific (e.g., 100.0m or 0)\",\n      \"unit\": \"Length (mm/inch)\",\n      \"affectsOutput\": \"Modifies the numerical text of vertical dimensions to match site datums rather than just local geometry.\"\n   "
      },
      "tokens_used": 11307,
      "error": null
    },
    "5": {
      "success": true,
      "data": {},
      "tokens_used": 14330,
      "error": null
    },
    "6": {
      "success": true,
      "data": {
        "markdown": "# PanelElementLayout2.mcr\n\n## Overview\nThis script automatically generates detailed dimension lines for Wall or Roof elements containing Structural Insulated Panels (SIPs) directly in Paper Space viewports. It is designed to create clean shop drawings by handling overall dimensions, individual panel joints, and openings with user-configurable styles.\n\n## Usage Environment\n| Space | Supported | Notes |\n|-------|-----------|-------|\n| Model Space | No | This script does not run in Model Space. |\n| Paper Space | Yes | This script must be inserted on a layout containing a viewport. |\n| Shop Drawing | Yes | Intended for creating production drawings and detailing. |\n\n## Prerequisites\n- **Required Entities**: A viewport on a Paper Space layout that is linked to a valid Element (Wall or Roof) containing SIPs.\n- **Minimum Beam Count**: 0\n- **Required Settings**: None. The script relies on the geometry of the selected element.\n\n## Usage Steps\n\n### Step 1: Launch Script\nCommand: `TSLINSERT` → Select `PanelElementLayout2.mcr` from the list.\n\n### Step 2: Select Viewport\n```\nCommand Line: Select a viewport\nAction: Click on the viewport in Paper Space that displays the wall or roof element you wish to dimension.\n```\n\n## Properties Panel Parameters\n\n| Parameter | Type | Default | Description |\n|-----------|------|---------|-------------|\n| Dimension Style Near | dropdown | *First available* | Sets the visual style (text size, arrows) for dimensions on the front face of the element. |\n| Dimension Style Far | dropdown | *First available* | Sets the visual style for dimensions on the back face of the element. |\n| Beam Dimstyle | dropdown | Combine with Near | Determines if internal beams are included in the dimension chain or ignored. |\n| Dimension Chain Spacing | number | 1 | The distance between stacked dimension lines (e.g., between overall and detailed dims). |\n| Dimension point tolerance | number | 0.125 | Threshold to merge nearby dimension points. Increase this if you see duplicate/cluttered dimensions. |\n| Limit Extension Lines | dropdown | Yes | If 'Yes', extension lines stop at the dimension line (cleaner look). If 'No', they extend to the geometry. |\n| Detail Level | dropdown | Extremes | 'Extremes' dimensions only total width/height. 'All Points' dimensions every opening, corner, and joint. |\n| Display Top Dim | dropdown | Yes | Toggles visibility of the top horizontal dimension line. |\n| Display Bottom Dim | dropdown | Yes | Toggles visibility of the bottom horizontal dimension line. |\n| Display Left Dim | dropdown | Yes | Toggles visibility of the left vertical dimension line. |\n| Display Right Dim | dropdown | Yes | Toggles visibility of the right vertical dimension line. |\n| Dim Connected Female Elements | dropdown | Yes | Includes dimensions for intersecting walls (e.g., partitions) attached to the main wall. |\n| Use Grips | dropdown | Yes | Enables interactive grips to drag and adjust dimension lines after creation. |\n| Top Dim Offset | number | 12 | Distance from the top of the element geometry to the first dimension line. |\n| Bottom Dim Offset | number | 12 | Distance from the bottom of the element to the first dimension line. |\n| Left Dim Offset | number | 12 | Distance from the left edge to the first dimension line. |\n| Right Dim Offset | number | 12 | Distance from the right edge to the first dimension line. |\n| Add Sip Points Left | dropdown | Yes | Includes SIP panel joint points on the left side in the dimension chain. |\n| Add Sip Points Right | dropdown | Yes | Includes SIP panel joint points on the right side in the dimension chain. |\n| Top Dim Type | dropdown | Delta | Style of measurement: 'Delta' (individual segments), 'Cummulative' (running total), or 'Both'. |\n| Bottom Dim Type | dropdown | Delta | Style of measurement for the bottom dimension chain. |\n| Left Dim Type | dropdown | Delta | Style of measurement for the left dimension chain. |\n| Right Dim Type | dropdown | Delta | Style of measurement for the right dimension chain. |\n| Off Lower Pt Left | number | 0 | Vertical offset for the start point of the left vertical dimension (useful to align with floor levels). |\n| Off Lower Pt Right | number | 0 | Vertical offset for the start point of the right vertical dimension. |\n| Add Base Dim | number | 0 | Adds an extra dimension segment below the wall bottom (e.g., for foundation height). |\n| Add Elevation | number | 0 | Adds a constant value to all vertical dimensions to convert them to Absolute Levels/RL. |\n\n## Right-Click Menu Options\n*No specific custom menu items were detected in the analysis. Standard context options (like Erase or Properties) apply.*\n\n## Settings Files\n- **Filename**: None specified\n- **Location**: N/A\n- **Purpose**: The script uses dimension styles defined in your current CAD template.\n\n## Tips\n- **Cleaning up clutter**: If your dimensions look messy with many overlapping points, try increasing the **Dimension point tolerance** (e.g., from 0.125 to 0.25 or 0.5) to merge points that are very close together.\n- **Interactive adjustment**: Ensure **Use Grips** is set to 'Yes'. After the script runs, you can select the dimensions in AutoCAD and use the blue grips to drag the lines into a clearer position without changing the properties.\n- **Absolute Levels**: To show RL (Reduced Levels) instead of just local heights, set **Add Elevation** to your ground level height (e.g., 100.0).\n- **Offsetting dimensions**: If the dimension text is colliding with the wall geometry, increase the **Dim Offset** values (Top, Bottom, Left, Right) to push the chains further away from the element.\n\n## FAQ\n- **Q: Why are no dimensions showing up?**\n  **A:** Check the **Display Top/Bot/Left/Right Dim** properties in the palette. Ensure the side you want to dimension is set to 'Yes'. Also, verify that the selected viewport actually contains an Element with SIPs.\n  \n- **Q: What is the difference between 'Delta' and 'Cumulative' dimension types?**\n  **A:** 'Delta' shows the size of each segment (e.g., 300, 400, 500). 'Cumulative' shows the running total distance from the start (e.g., 300, 700, 1200). 'Both' will display both values if space permits.\n\n- **Q: How do I dimension the wall height relative to the floor finish rather than the bottom plate?**\n  **A:** Use the **Off Lower Pt Left** or **Off Lower Pt Right** parameter. Enter the vertical distance from the bottom of the wall model to your desired reference line (e.g., the floor finish)."
      },
      "tokens_used": 9163,
      "error": null
    }
  }
}